HISTORY.rst
LICENSE.rst
MANIFEST.in
README.rst
setup.py
src/bda/__init__.py
src/bda.awstatsparser.egg-info/PKG-INFO
src/bda.awstatsparser.egg-info/SOURCES.txt
src/bda.awstatsparser.egg-info/dependency_links.txt
src/bda.awstatsparser.egg-info/entry_points.txt
src/bda.awstatsparser.egg-info/namespace_packages.txt
src/bda.awstatsparser.egg-info/not-zip-safe
src/bda.awstatsparser.egg-info/requires.txt
src/bda.awstatsparser.egg-info/top_level.txt
src/bda/awstatsparser/__init__.py
src/bda/awstatsparser/defaults.py
src/bda/awstatsparser/parser.py