Metadata-Version: 1.1
Name: bda.awstatsparser
Version: 1.2.1
Summary: Library for parsing of awstats result files
Home-page: http://pypi.python.org/pypi/bda.awstatsparser
Author: BlueDynamics Alliance
Author-email: dev@bluedynamics.com
License: GPL
Keywords: plone statistics
Platform: UNKNOWN
Classifier: Development Status :: 5 - Production/Stable
Classifier: License :: OSI Approved :: GNU General Public License (GPL)
Classifier: Operating System :: OS Independent
Classifier: Programming Language :: Python
